signal_cli_socket.py
signal_cli_socket-0.7.dist-info/LICENSE
signal_cli_socket-0.7.dist-info/WHEEL
signal_cli_socket-0.7.dist-info/METADATA
signal_cli_socket-0.7.dist-info/RECORD
