Metadata-Version: 2.1
Name: signal-cli-socket
Version: 0.7
Summary: A package to use with the signal-cli made by AsamK.
Home-page: https://github.com/Nickwasused/signal-cli-socket
License: MPL-2.0
Author: Nickwasused
Author-email: contact.nickwasused.fa6c8@simplelogin.co
Classifier: License :: OSI Approved
Classifier: License :: OSI Approved :: Mozilla Public License 2.0 (MPL 2.0)
Classifier: Operating System :: OS Independent
Classifier: Programming Language :: Python :: 2
Classifier: Programming Language :: Python :: 2.7
Classifier: Programming Language :: Python :: 3
Classifier: Programming Language :: Python :: 3.4
Classifier: Programming Language :: Python :: 3.5
Classifier: Programming Language :: Python :: 3.6
Classifier: Programming Language :: Python :: 3.7
Classifier: Programming Language :: Python :: 3.8
Classifier: Programming Language :: Python :: 3.9
Classifier: Programming Language :: Python :: 3.10
Classifier: Programming Language :: Python :: 3
Classifier: Programming Language :: Python :: 3 :: Only
Project-URL: Bug Tracker, https://github.com/Nickwasused/signal-cli-socket/issues
Project-URL: Documentation, https://github.com/Nickwasused/signal-cli-socket
Project-URL: Repository, https://github.com/Nickwasused/signal-cli-socket
